tsetsen/__init__.py
tsetsen/client.py
tsetsen/exceptions.py
tsetsen/tsetsen_tts_pb2.py
tsetsen/tsetsen_tts_pb2_grpc.py
tsetsen/auth/__init__.py
tsetsen/auth/api_key.py
tsetsen/models/__init__.py
tsetsen/models/requests.py
tsetsen/models/responses.py
tsetsen/utils/__init__.py
tsetsen/utils/retry.py
tsetsen-0.1.10.dist-info/METADATA
tsetsen-0.1.10.dist-info/WHEEL
tsetsen-0.1.10.dist-info/top_level.txt
tsetsen-0.1.10.dist-info/RECORD
