Metadata-Version: 2.4
Name: tsetsen
Version: 0.1.10
Summary: Python SDK for the Tsetsen, Mongolian Text-to-Speech API
Home-page: 
Author: Tsetsen AI
Author-email: info@tsetsen.ai
License: MIT
Keywords: tts,text-to-speech,api,grpc,speech synthesis
Classifier: Development Status :: 4 - Beta
Classifier: Intended Audience :: Developers
Classifier: License :: OSI Approved :: MIT License
Classifier: Programming Language :: Python :: 3.10
Classifier: Programming Language :: Python :: 3.11
Classifier: Topic :: Software Development :: Libraries
Classifier: Topic :: Multimedia :: Sound/Audio :: Speech
Requires-Python: >=3.10
Requires-Dist: grpcio>=1.40.0
Requires-Dist: protobuf>=3.19.0
Provides-Extra: dev
Requires-Dist: pytest>=6.0.0; extra == "dev"
Requires-Dist: black>=21.5b2; extra == "dev"
Requires-Dist: mypy>=0.812; extra == "dev"
Requires-Dist: grpcio-tools>=1.40.0; extra == "dev"
Requires-Dist: twine>=3.4.1; extra == "dev"
Dynamic: author
Dynamic: author-email
Dynamic: classifier
Dynamic: description
Dynamic: description-content-type
Dynamic: keywords
Dynamic: license
Dynamic: provides-extra
Dynamic: requires-dist
Dynamic: requires-python
Dynamic: summary
